bidq/__init__.py
bidq/client.py
bidq/exceptions.py
bidq/utils.py
bidq-0.0.1.dist-info/LICENSE
bidq-0.0.1.dist-info/METADATA
bidq-0.0.1.dist-info/WHEEL
bidq-0.0.1.dist-info/top_level.txt
bidq-0.0.1.dist-info/RECORD
