Metadata-Version: 2.1
Name: bidq
Version: 0.0.1
Summary: Python SDK for bidq
Home-page: https://github.com/bidq/pybidq
Author: Alon Niv
Author-email: oakfang@gmail.com
License: UNKNOWN
Platform: UNKNOWN
Classifier: Programming Language :: Python :: 3
Classifier: License :: OSI Approved :: MIT License
Classifier: Operating System :: OS Independent
Requires-Python: >=3.7
